{"assets/biwamusume/アブラヒガイ.png":["assets/biwamusume/アブラヒガイ.png"],"assets/biwamusume/イサザ.png":["assets/biwamusume/イサザ.png"],"assets/biwamusume/イワトコナマズ.png":["assets/biwamusume/イワトコナマズ.png"],"assets/biwamusume/ウツセミカジカ.png":["assets/biwamusume/ウツセミカジカ.png"],"assets/biwamusume/ウナギ.png":["assets/biwamusume/ウナギ.png"],"assets/biwamusume/オクチバス.png":["assets/biwamusume/オクチバス.png"],"assets/biwamusume/コイ.png":["assets/biwamusume/コイ.png"],"assets/biwamusume/ゴリ.png":["assets/biwamusume/ゴリ.png"],"assets/biwamusume/スゴモロコ.png":["assets/biwamusume/スゴモロコ.png"],"assets/biwamusume/スジエビ.png":["assets/biwamusume/スジエビ.png"],"assets/biwamusume/スッポン.png":["assets/biwamusume/スッポン.png"],"assets/biwamusume/セタシジミ.png":["assets/biwamusume/セタシジミ.png"],"assets/biwamusume/タテボシガイ.png":["assets/biwamusume/タテボシガイ.png"],"assets/biwamusume/トウヨシノボリ.png":["assets/biwamusume/トウヨシノボリ.png"],"assets/biwamusume/ドジョウ.png":["assets/biwamusume/ドジョウ.png"],"assets/biwamusume/ニゴイ.png":["assets/biwamusume/ニゴイ.png"],"assets/biwamusume/ニゴロブナ.png":["assets/biwamusume/ニゴロブナ.png"],"assets/biwamusume/ヌマチチブ.png":["assets/biwamusume/ヌマチチブ.png"],"assets/biwamusume/ハクレン.png":["assets/biwamusume/ハクレン.png"],"assets/biwamusume/ハス.png":["assets/biwamusume/ハス.png"],"assets/biwamusume/ビワコオオナマズ.png":["assets/biwamusume/ビワコオオナマズ.png"],"assets/biwamusume/ビワヒガイ.png":["assets/biwamusume/ビワヒガイ.png"],"assets/biwamusume/ビワマス.png":["assets/biwamusume/ビワマス.png"],"assets/biwamusume/フナ.png":["assets/biwamusume/フナ.png"],"assets/biwamusume/ブルーギル.png":["assets/biwamusume/ブルーギル.png"],"assets/biwamusume/ホンモロコ.png":["assets/biwamusume/ホンモロコ.png"],"assets/biwamusume/ムギツク.png":["assets/biwamusume/ムギツク.png"],"assets/biwamusume/メダカ.png":["assets/biwamusume/メダカ.png"],"assets/biwamusume/ユアユ.png":["assets/biwamusume/ユアユ.png"],"assets/biwamusume/ライギョ.png":["assets/biwamusume/ライギョ.png"],"assets/biwamusume/ワカサギ.png":["assets/biwamusume/ワカサギ.png"],"assets/biwamusume/ワタカ.png":["assets/biwamusume/ワタカ.png"],"assets/diagnostic_page_background.png":["assets/diagnostic_page_background.png"],"assets/logo.png":["assets/logo.png"],"assets/result_page_above-bg.png":["assets/result_page_above-bg.png"],"assets/result_page_profile-image.png":["assets/result_page_profile-image.png"],"assets/result_page_under-bg.png":["assets/result_page_under-bg.png"],"assets/top_bg.png":["assets/top_bg.png"],"packages/cupertino_icons/assets/CupertinoIcons.ttf":["packages/cupertino_icons/assets/CupertinoIcons.ttf"]}